data360/__init__.py
data360/api.py
data360/config.py
data360/models.py
data360/server.py
data360/mcp_server/__init__.py
data360/mcp_server/__main__.py
data360/mcp_server/_server_definition.py
data360/mcp_server/prompts.py
data360/mcp_server/resources.py
data360/mcp_server/tools.py
data360_mcp-0.1.1.dist-info/licenses/LICENSE
data360_mcp-0.1.1.dist-info/METADATA
data360_mcp-0.1.1.dist-info/WHEEL
data360_mcp-0.1.1.dist-info/top_level.txt
data360_mcp-0.1.1.dist-info/RECORD
