Metadata-Version: 2.4
Name: data360-mcp
Version: 0.1.1
Summary: Data360 MCP Project
Requires-Python: >=3.10
License-File: LICENSE
Requires-Dist: fastmcp>=2.12.4
Requires-Dist: mcp>=1.18.0
Requires-Dist: fastapi>=0.115.0
Requires-Dist: uvicorn[standard]>=0.30.0
Requires-Dist: langchain-mcp-adapters>=0.1.13
Requires-Dist: typer>=0.20.1
Dynamic: license-file
